mujoco_tools/__init__.py
mujoco_tools/cli.py
mujoco_tools/data_fromat.md
mujoco_tools/data_processor.py
mujoco_tools/inverse_kinematics.py
mujoco_tools/mujoco_loader.py
mujoco_tools/player.py
mujoco_tools/recorder.py
mujoco_tools/tools.py
mujoco_tools-0.1.1.dist-info/METADATA
mujoco_tools-0.1.1.dist-info/WHEEL
mujoco_tools-0.1.1.dist-info/entry_points.txt
mujoco_tools-0.1.1.dist-info/licenses/LICENSE
mujoco_tools-0.1.1.dist-info/RECORD
