Metadata-Version: 2.4
Name: mujoco-tools
Version: 0.1.1
Summary: A toolkit for MuJoCo simulation and visualization
Project-URL: Homepage, https://github.com/shanningzhuang/mujoco_tools
Project-URL: Repository, https://github.com/shanningzhuang/mujoco_tools
Project-URL: Documentation, https://github.com/shanningzhuang/mujoco_tools
Project-URL: Issues, https://github.com/shanningzhuang/mujoco_tools/issues
Author-email: Shanning Zhuang <shanning.zhuang@outlook.com>
License: MIT
License-File: LICENSE
Keywords: mujoco,robotics,simulation,visualization
Classifier: Development Status :: 3 - Alpha
Classifier: Intended Audience :: Developers
Classifier: Intended Audience :: Science/Research
Classifier: License :: OSI Approved :: MIT License
Classifier: Operating System :: OS Independent
Classifier: Programming Language :: Python :: 3
Classifier: Programming Language :: Python :: 3.12
Classifier: Topic :: Scientific/Engineering :: Artificial Intelligence
Classifier: Topic :: Scientific/Engineering :: Physics
Requires-Python: >=3.12
Requires-Dist: imageio>=2.9.0
Requires-Dist: matplotlib>=3.4.0
Requires-Dist: mujoco>=3.2.0
Requires-Dist: numpy>=1.23.0
Requires-Dist: opencv-python>=4.5.0
Requires-Dist: tqdm>=4.62.0
Provides-Extra: dev
Requires-Dist: mypy>=1.0.0; extra == 'dev'
Requires-Dist: pytest-cov>=4.1.0; extra == 'dev'
Requires-Dist: pytest>=7.0.0; extra == 'dev'
Requires-Dist: ruff>=0.1.0; extra == 'dev'
Provides-Extra: docs
Requires-Dist: sphinx-rtd-theme>=1.0.0; extra == 'docs'
Requires-Dist: sphinx>=4.0.0; extra == 'docs'
